Trapalyzer/__init__.py
Trapalyzer/_version.py
Trapalyzer/measurement.py
Trapalyzer/napari_functions.py
Trapalyzer/segmentation.py
Trapalyzer/widgets.py
Trapalyzer-0.0.7.dist-info/License.txt
Trapalyzer-0.0.7.dist-info/METADATA
Trapalyzer-0.0.7.dist-info/WHEEL
Trapalyzer-0.0.7.dist-info/entry_points.txt
Trapalyzer-0.0.7.dist-info/top_level.txt
Trapalyzer-0.0.7.dist-info/RECORD
