Metadata-Version: 2.1
Name: Trapalyzer
Version: 0.0.7
Summary: Automatic feature detection and quantification for in-vitro NETosis experiments plugin for PartSeg
Home-page: https://github.com/Czaki/Trapalyzer
Author: Grzegorz Bokota, Michał Ciach
Author-email: g.bokota@uw.edu.pl, m_ciach@student.uw.edu.pl
License: MIT
Classifier: License :: OSI Approved :: MIT License
Classifier: Operating System :: OS Independent
Classifier: Programming Language :: Python :: 3
Classifier: Programming Language :: Python :: 3 :: Only
Classifier: Programming Language :: Python :: 3.7
Classifier: Programming Language :: Python :: 3.8
Classifier: Programming Language :: Python :: 3.9
Classifier: Programming Language :: Python :: 3.10
Requires-Python: >=3.7
License-File: License.txt
Requires-Dist: PartSeg (>=0.14.0)
Requires-Dist: SimpleITK
Requires-Dist: magicgui (>=0.4.0)
Requires-Dist: napari
Requires-Dist: nme (>=0.1.3)
Requires-Dist: numpy
Requires-Dist: pydantic
